libpythonpro/__init__.py
libpythonpro/github_api.py
libpythonpro_gwp-0.1.dist-info/LICENSE
libpythonpro_gwp-0.1.dist-info/METADATA
libpythonpro_gwp-0.1.dist-info/WHEEL
libpythonpro_gwp-0.1.dist-info/top_level.txt
libpythonpro_gwp-0.1.dist-info/RECORD
